{
    "versionLabel": "1.0",
    "uuid": "2fd72c58-d66c-4144-aea6-81e1aaaa8b26",
    "appKeys": {},
    "longName": "Wow Such Watchface",
    "versionCode": 1,
    "capabilities": [
        ""
    ],
    "shortName": "Wow",
    "companyName": "mkbehr",
    "watchapp": {
        "watchface": true
    },
    "resources": {
        "media": [
            {
                "type": "font",
                "name": "COMIC_SANS_21",
                "file": "fonts/Comic Sans MS.ttf"
            },
            {
                "type": "font",
                "name": "COMIC_SANS_18",
                "file": "fonts/Comic Sans MS.ttf"
            },
            {
                "type": "font",
                "name": "COMIC_SANS_10",
                "file": "fonts/Comic Sans MS.ttf"
            },
            {
                "type": "font",
                "name": "COMIC_SANS_16",
                "file": "fonts/Comic Sans MS.ttf"
            },
            {
                "type": "font",
                "name": "COMIC_SANS_BOLD_36",
                "file": "fonts/Comic Sans MS Bold.ttf"
            },
            {
                "type": "font",
                "name": "COMIC_SANS_BOLD_21",
                "file": "fonts/Comic Sans MS Bold.ttf"
            },
            {
                "type": "png",
                "name": "WOW_SUCH_FACE",
                "file": "images/shibeface.png"
            }
        ]
    }
}
